five9_stats/__init__.py
five9_stats/api/__init__.py
five9_stats/api/client.py
five9_stats/api/interval.py
five9_stats/api/snapshot.py
five9_stats/models/__init__.py
five9_stats/models/common.py
five9_stats/models/interval.py
five9_stats/models/snapshot.py
five9_stats-0.1.0.dist-info/METADATA
five9_stats-0.1.0.dist-info/WHEEL
five9_stats-0.1.0.dist-info/top_level.txt
five9_stats-0.1.0.dist-info/RECORD
