Metadata-Version: 2.4
Name: five9-stats
Version: 0.1.0
Summary: Python client library for Five9 Statistics APIs
Home-page: https://github.com/JamesSmart/five9-stats
Author: Five9 Stats Library
Author-email: james.smart@five9.com
Classifier: Programming Language :: Python :: 3
Classifier: Programming Language :: Python :: 3.7
Classifier: Programming Language :: Python :: 3.8
Classifier: Programming Language :: Python :: 3.9
Classifier: Programming Language :: Python :: 3.10
Classifier: License :: OSI Approved :: MIT License
Classifier: Operating System :: OS Independent
Requires-Python: >=3.7
Requires-Dist: aiohttp>=3.8.0
Requires-Dist: pydantic>=1.9.0
Dynamic: author
Dynamic: author-email
Dynamic: classifier
Dynamic: description
Dynamic: description-content-type
Dynamic: home-page
Dynamic: requires-dist
Dynamic: requires-python
Dynamic: summary
